skolemizer/__init__.py
skolemizer/skolemizer.py
skolemizer/testutils.py
skolemizer-2.0.1.dist-info/LICENSE
skolemizer-2.0.1.dist-info/METADATA
skolemizer-2.0.1.dist-info/WHEEL
skolemizer-2.0.1.dist-info/RECORD
