Metadata-Version: 2.1
Name: skolemizer
Version: 2.0.1
Summary: A library with utils for performing Skolemization on blank nodes (RDF)
Home-page: https://github.com/Informasjonsforvaltning/skolemizer
License: Apache-2.0
Author: Stig B. Dørmænen
Author-email: stigbd@gmail.com
Requires-Python: >=3.10,<4.0
Classifier: License :: OSI Approved :: Apache Software License
Classifier: Operating System :: OS Independent
Classifier: Programming Language :: Python :: 3
Classifier: Programming Language :: Python :: 3.10
Classifier: Programming Language :: Python :: 3.11
Classifier: Programming Language :: Python :: 3.12
Classifier: Programming Language :: Python :: 3.13
Project-URL: Documentation, https://skolemizer.readthedocs.io
Project-URL: Repository, https://github.com/Informasjonsforvaltning/skolemizer
